{
    "characterName": "11",
    "item_Equipments": {
        "SD_equipments": [
            {
                "id": 1101001,
                "count": 1,
                "EquipmentType": 0,
                "Level": 1,
                "Xp": 0,
                "NextXP": 0,
                "Durability": 100.0,
                "ChangedOption": {
                    "Value": NaN,
                    "Stat": 16,
                    "How": 6
                },
                "SD_staticOption": [
                    {
                        "Value": 1327.953857421875,
                        "Stat": 1
                    },
                    {
                        "Value": 1.2999999523162842,
                        "Stat": 4
                    },
                    {
                        "Value": 659.7432250976563,
                        "Stat": 0
                    }
                ],
                "SD_dynamicOption": [
                    {
                        "Value": 713.8292236328125,
                        "Stat": 7,
                        "How": 5
                    },
                    {
                        "Value": 0.14023780822753907,
                        "Stat": 15,
                        "How": 4
                    },
                    {
                        "Value": 0.10362369567155838,
                        "Stat": 1,
                        "How": 4
                    }
                ]
            }
        ]
    },
    "item_Inventory": {
        "SD_equipments": [],
        "SD_etcs": [
            {
                "ItemData": {
                    "id": 3666001,
                    "count": 7
                },
                "LocationX": 0,
                "LocationY": 0
            }
        ]
    },
    "item_Storage": {
        "SD_equipments": [],
        "SD_etcs": []
    },
    "PlayerExp": 5000
}